<ProgramSettings>
  <Window>
    <Left>748</Left>
    <Top>253</Top>
    <Width>472</Width>
    <Height>345</Height>
  </Window>
  <Options>
    <ShowValidMoves>True</ShowValidMoves>
    <PreviewMoves>False</PreviewMoves>
    <AnimateMoves>True</AnimateMoves>
    <BoardColor>-16744448</BoardColor>
    <ValidMoveColor>-16732160</ValidMoveColor>
    <ActiveSquareColor>-16719872</ActiveSquareColor>
    <MoveIndicatorColor>-65536</MoveIndicatorColor>
    <ComputerPlaysBlack>False</ComputerPlaysBlack>
    <ComputerPlaysWhite>True</ComputerPlaysWhite>
    <BlackDifficulty>1</BlackDifficulty>
    <WhiteDifficulty>1</WhiteDifficulty>
    <BlackFullSailAiMode>0</BlackFullSailAiMode>
    <BlackTranspositionTable>False</BlackTranspositionTable>
    <BlackMctsSimulationNumber>1000</BlackMctsSimulationNumber>
    <BlackCachingMemoryNumber>100</BlackCachingMemoryNumber>
    <WhiteFullSailAiMode>0</WhiteFullSailAiMode>
    <WhiteTranspositionTable>False</WhiteTranspositionTable>
    <WhiteMctsSimulationNumber>1000</WhiteMctsSimulationNumber>
    <WhiteCachingMemoryNumber>100</WhiteCachingMemoryNumber>
  </Options>
  <Statistics>
    <BlackWins>0</BlackWins>
    <WhiteWins>0</WhiteWins>
    <OverallDraws>0</OverallDraws>
    <BlackTotalScore>0</BlackTotalScore>
    <WhiteTotalScore>0</WhiteTotalScore>
    <ComputerWins>0</ComputerWins>
    <UserWins>0</UserWins>
    <VsComputerDraws>0</VsComputerDraws>
    <ComputerTotalScore>0</ComputerTotalScore>
    <UserTotalScore>0</UserTotalScore>
  </Statistics>
</ProgramSettings>